{
  "Sources": [
    {
      "source": "YB12",
      "yb_number": 12,
      "reference": "WolfChase25",
      "dist": 6.47,
      "e_dist": 2.39,
      "dist_c": 8.61,
      "dist_m": 8.65,
      "e_dist_m": 0.09,
      "stat_m": "NO_KDA",
      "pfar": 0.5,
      "dist_r1": 6.47,
      "e_dist_r1": 2.39,
      "pint_r1": 0.65,
      "arm_r1": "?",
      "dist_r2": 11.2,
      "e_dist_r2": 1.58,
      "pint_r2": 0.35,
      "arm_r2": "3kF?",
      "diam": null,
      "e_diam": null,
      "mass": null,
      "e_mass": null,
      "blum": null,
      "e_blum": null,
      "lmrat": null,
      "e_lmrat": null,
      "temp": null,
      "e_temp": null,
      "lrat": null,
      "e_lrat": null,
      "tbol": null,
      "e_tbol": null,
      "sigma": null,
      "e_sigma": null,
      "glon": 0.38154,
      "glat": 0.01656,
      "mwpr": 0.00565,
      "e_glon": 0.00087,
      "e_glat": 0.00073,
      "e_mwpr": 0.00215,
      "hrate": 0.53,
      "f8": 6.3362,
      "e_f8": 0.2989,
      "f12": null,
      "e_f12": null,
      "f24": null,
      "e_f24": null,
      "f70": 254.843,
      "e_f70": 0.2997,
      "n8": 5,
      "n12": 0,
      "n24": 0,
      "n70": 5,
      "f_sat": "0110",
      "f_multi": 0,
      "f_nosrc": "0000",
      "f_pconf": "0000",
      "f_cext": 0,
      "vlsr": 33.75,
      "e_vlsr": 0.13,
      "stype": "SP",
      "vlsr_g": null,
      "vlsr_s": 33.75,
      "vlsr_f": null,
      "vlsr_t": null,
      "vlsr_dht": null,
      "vlsr_dgt": null,
      "dgt": null,
      "vlsr_c": 36.0,
      "vlsr_m": 32.03,
      "e_vlsr_m": 0.83,
      "higal": "HIGALBM0.3797+0.0184",
      "agal": "G000.3788+0.0172",
      "corn": null,
      "corn_t": null,
      "rms": null,
      "rms_t": null,
      "wise": "G000.382+00.017",
      "wise_t": "K"
    }
  ]
}
