{
  "Sources": [
    {
      "source": "YB1244",
      "yb_number": 1244,
      "reference": "WolfChase25",
      "dist": 2.24,
      "e_dist": 0.18,
      "dist_c": 12.17,
      "dist_m": 12.17,
      "e_dist_m": 0.41,
      "stat_m": "NO_KDA",
      "pfar": 0.5,
      "dist_r1": 2.24,
      "e_dist_r1": 0.18,
      "pint_r1": 0.84,
      "arm_r1": "SgN",
      "dist_r2": 10.14,
      "e_dist_r2": 0.32,
      "pint_r2": 0.16,
      "arm_r2": "SgF",
      "diam": 0.18,
      "e_diam": 0.01,
      "mass": 13.39,
      "e_mass": 12.49,
      "blum": 977.16,
      "e_blum": 250.71,
      "lmrat": 72.97,
      "e_lmrat": 70.57,
      "temp": 27.1,
      "e_temp": 1.9,
      "lrat": 290.7,
      "e_lrat": 58.14,
      "tbol": 48.97,
      "e_tbol": 9.79,
      "sigma": 0.11,
      "e_sigma": 0.1,
      "glon": 31.42702,
      "glat": -0.13981,
      "mwpr": 0.00434,
      "e_glon": 0.00051,
      "e_glat": 0.00056,
      "e_mwpr": 0.00106,
      "hrate": 0.77,
      "f8": 1.4297,
      "e_f8": 0.3257,
      "f12": 0.5182,
      "e_f12": 0.3346,
      "f24": 1.6696,
      "e_f24": 0.2374,
      "f70": 46.9738,
      "e_f70": 0.2955,
      "n8": 6,
      "n12": 6,
      "n24": 6,
      "n70": 6,
      "f_sat": "0000",
      "f_multi": 0,
      "f_nosrc": "0000",
      "f_pconf": "0001",
      "f_cext": 0,
      "vlsr": 41.17,
      "e_vlsr": 0.1,
      "stype": "MP:1",
      "vlsr_g": 41.17,
      "vlsr_s": null,
      "vlsr_f": null,
      "vlsr_t": null,
      "vlsr_dht": null,
      "vlsr_dgt": null,
      "dgt": null,
      "vlsr_c": 31.6,
      "vlsr_m": 31.6,
      "e_vlsr_m": 0.17,
      "higal": "HIGALBM31.4266-0.1405",
      "agal": "G031.4270-0.1389",
      "corn": null,
      "corn_t": null,
      "rms": null,
      "rms_t": null,
      "wise": "G031.426-00.140",
      "wise_t": "G"
    }
  ]
}
