{
  "Sources": [
    {
      "source": "YB1346",
      "yb_number": 1346,
      "reference": "WolfChase25",
      "dist": 12.58,
      "e_dist": 0.65,
      "dist_c": 8.17,
      "dist_m": 8.1,
      "e_dist_m": 0.53,
      "stat_m": "NO_KDA",
      "pfar": 0.5,
      "dist_r1": 12.58,
      "e_dist_r1": 0.65,
      "pint_r1": 0.53,
      "arm_r1": "Per",
      "dist_r2": 0.24,
      "e_dist_r2": 0.02,
      "pint_r2": 0.24,
      "arm_r2": "AqR",
      "diam": 1.02,
      "e_diam": 0.05,
      "mass": 1351.43,
      "e_mass": 139.67,
      "blum": 3559.7,
      "e_blum": 367.85,
      "lmrat": 2.63,
      "e_lmrat": 0.38,
      "temp": 14.4,
      "e_temp": 0.4,
      "lrat": 39.5,
      "e_lrat": 7.9,
      "tbol": 42.56,
      "e_tbol": 8.51,
      "sigma": 0.35,
      "e_sigma": 0.04,
      "glon": 33.30247,
      "glat": 0.09427,
      "mwpr": 0.00332,
      "e_glon": 0.0009,
      "e_glat": 0.00038,
      "e_mwpr": 0.00251,
      "hrate": 0.31,
      "f8": 0.1735,
      "e_f8": 0.8562,
      "f12": 0.0697,
      "e_f12": 1.2672,
      "f24": 0.134,
      "e_f24": 1.0005,
      "f70": 4.3281,
      "e_f70": 0.8626,
      "n8": 5,
      "n12": 5,
      "n24": 5,
      "n70": 5,
      "f_sat": "0000",
      "f_multi": 1,
      "f_nosrc": "0000",
      "f_pconf": "1010",
      "f_cext": 0,
      "vlsr": 9.92,
      "e_vlsr": 0.1,
      "stype": "MP:2",
      "vlsr_g": 9.92,
      "vlsr_s": null,
      "vlsr_f": null,
      "vlsr_t": null,
      "vlsr_dht": null,
      "vlsr_dgt": 9.92,
      "dgt": "HOPS_NH3",
      "vlsr_c": 98.0,
      "vlsr_m": 98.9,
      "e_vlsr_m": 0.3,
      "higal": "HIGALBM33.3052+0.0959",
      "agal": null,
      "corn": null,
      "corn_t": null,
      "rms": null,
      "rms_t": null,
      "wise": null,
      "wise_t": null
    }
  ]
}
