{
  "Sources": [
    {
      "source": "YB1744",
      "yb_number": 1744,
      "reference": "WolfChase25",
      "dist": 11.13,
      "e_dist": 0.32,
      "dist_c": 11.46,
      "dist_m": 11.46,
      "e_dist_m": 0.45,
      "stat_m": "NO_KDA",
      "pfar": 0.5,
      "dist_r1": 11.13,
      "e_dist_r1": 0.32,
      "pint_r1": 0.95,
      "arm_r1": "Per",
      "dist_r2": 0.3,
      "e_dist_r2": 0.05,
      "pint_r2": 0.05,
      "arm_r2": "AqR",
      "diam": 0.59,
      "e_diam": 0.02,
      "mass": 807.79,
      "e_mass": 63.24,
      "blum": 6373.55,
      "e_blum": 366.49,
      "lmrat": 7.89,
      "e_lmrat": 0.77,
      "temp": 18.1,
      "e_temp": 0.5,
      "lrat": 69.5,
      "e_lrat": 13.9,
      "tbol": 47.99,
      "e_tbol": 9.6,
      "sigma": 0.61,
      "e_sigma": 0.05,
      "glon": 41.89769,
      "glat": -0.15402,
      "mwpr": 0.0032,
      "e_glon": 0.00044,
      "e_glat": 0.00047,
      "e_mwpr": 0.00131,
      "hrate": 0.56,
      "f8": 0.3126,
      "e_f8": 0.1778,
      "f12": 0.0784,
      "e_f12": 0.2639,
      "f24": 0.4121,
      "e_f24": 0.3057,
      "f70": 11.9011,
      "e_f70": 0.309,
      "n8": 6,
      "n12": 6,
      "n24": 6,
      "n70": 6,
      "f_sat": "0000",
      "f_multi": 1,
      "f_nosrc": "0000",
      "f_pconf": "0000",
      "f_cext": 0,
      "vlsr": 14.39,
      "e_vlsr": 0.1,
      "stype": "SP",
      "vlsr_g": 14.39,
      "vlsr_s": null,
      "vlsr_f": null,
      "vlsr_t": null,
      "vlsr_dht": null,
      "vlsr_dgt": null,
      "dgt": null,
      "vlsr_c": 14.5,
      "vlsr_m": 14.49,
      "e_vlsr_m": 0.06,
      "higal": "HIGALBM41.8984-0.1535",
      "agal": null,
      "corn": null,
      "corn_t": null,
      "rms": null,
      "rms_t": null,
      "wise": null,
      "wise_t": null
    }
  ]
}
