{
  "Sources": [
    {
      "source": "YB2300",
      "yb_number": 2300,
      "reference": "WolfChase25",
      "dist": 4.36,
      "e_dist": 0.62,
      "dist_c": 6.56,
      "dist_m": 6.56,
      "e_dist_m": 0.74,
      "stat_m": "NO_KDA",
      "pfar": 0.5,
      "dist_r1": 4.36,
      "e_dist_r1": 0.62,
      "pint_r1": 1.0,
      "arm_r1": "LoS",
      "dist_r2": 0.0,
      "e_dist_r2": 0.0,
      "pint_r2": 0.0,
      "arm_r2": null,
      "diam": 0.71,
      "e_diam": 0.1,
      "mass": 165.83,
      "e_mass": 163.46,
      "blum": 536.8,
      "e_blum": 186.64,
      "lmrat": 3.24,
      "e_lmrat": 3.38,
      "temp": 15.2,
      "e_temp": 0.4,
      "lrat": 42.2,
      "e_lrat": 8.44,
      "tbol": 42.81,
      "e_tbol": 8.56,
      "sigma": 0.09,
      "e_sigma": 0.09,
      "glon": 54.94188,
      "glat": -0.23299,
      "mwpr": 0.00443,
      "e_glon": 0.00121,
      "e_glat": 0.00039,
      "e_mwpr": 0.00199,
      "hrate": 0.54,
      "f8": 0.4908,
      "e_f8": 0.4087,
      "f12": 0.1826,
      "e_f12": 0.6844,
      "f24": 0.3012,
      "e_f24": 0.5118,
      "f70": 4.2344,
      "e_f70": 0.4527,
      "n8": 6,
      "n12": 6,
      "n24": 6,
      "n70": 6,
      "f_sat": "0000",
      "f_multi": 1,
      "f_nosrc": "0000",
      "f_pconf": "0000",
      "f_cext": 0,
      "vlsr": 36.27,
      "e_vlsr": 0.1,
      "stype": "SP",
      "vlsr_g": 36.27,
      "vlsr_s": null,
      "vlsr_f": null,
      "vlsr_t": null,
      "vlsr_dht": null,
      "vlsr_dgt": null,
      "dgt": null,
      "vlsr_c": 36.2,
      "vlsr_m": 36.16,
      "e_vlsr_m": 0.05,
      "higal": "HIGALBM54.9389-0.2322",
      "agal": null,
      "corn": null,
      "corn_t": null,
      "rms": null,
      "rms_t": null,
      "wise": null,
      "wise_t": null
    }
  ]
}
