{
  "Sources": [
    {
      "source": "YB2846",
      "yb_number": 2846,
      "reference": "WolfChase25",
      "dist": 1.96,
      "e_dist": 0.77,
      "dist_c": null,
      "dist_m": null,
      "e_dist_m": null,
      "stat_m": null,
      "pfar": 0.5,
      "dist_r1": 1.96,
      "e_dist_r1": 0.77,
      "pint_r1": 0.45,
      "arm_r1": "Loc",
      "dist_r2": 1.58,
      "e_dist_r2": 0.08,
      "pint_r2": 0.31,
      "arm_r2": null,
      "diam": null,
      "e_diam": null,
      "mass": null,
      "e_mass": null,
      "blum": null,
      "e_blum": null,
      "lmrat": null,
      "e_lmrat": null,
      "temp": null,
      "e_temp": null,
      "lrat": null,
      "e_lrat": null,
      "tbol": null,
      "e_tbol": null,
      "sigma": null,
      "e_sigma": null,
      "glon": 79.73609,
      "glat": 3.42228,
      "mwpr": 0.00411,
      "e_glon": 0.00088,
      "e_glat": 0.00046,
      "e_mwpr": 0.0014,
      "hrate": 0.21,
      "f8": 0.1443,
      "e_f8": 0.5278,
      "f12": 0.0662,
      "e_f12": 0.4108,
      "f24": 0.1179,
      "e_f24": 0.4039,
      "f70": 1.1038,
      "e_f70": 0.6137,
      "n8": 6,
      "n12": 6,
      "n24": 6,
      "n70": 6,
      "f_sat": "0000",
      "f_multi": 0,
      "f_nosrc": "0000",
      "f_pconf": "1000",
      "f_cext": 0,
      "vlsr": -4.32,
      "e_vlsr": 0.65,
      "stype": "SP",
      "vlsr_g": null,
      "vlsr_s": null,
      "vlsr_f": null,
      "vlsr_t": null,
      "vlsr_dht": -4.32,
      "vlsr_dgt": null,
      "dgt": null,
      "vlsr_c": null,
      "vlsr_m": null,
      "e_vlsr_m": null,
      "higal": null,
      "agal": null,
      "corn": null,
      "corn_t": null,
      "rms": null,
      "rms_t": null,
      "wise": null,
      "wise_t": null
    }
  ]
}
