{
  "Sources": [
    {
      "source": "YB2923",
      "yb_number": 2923,
      "reference": "WolfChase25",
      "dist": 5.39,
      "e_dist": 0.55,
      "dist_c": 5.67,
      "dist_m": 5.67,
      "e_dist_m": 0.66,
      "stat_m": "NO_AMB",
      "pfar": 1.0,
      "dist_r1": 5.39,
      "e_dist_r1": 0.55,
      "pint_r1": 1.0,
      "arm_r1": "Per",
      "dist_r2": 0.0,
      "e_dist_r2": 0.0,
      "pint_r2": 0.0,
      "arm_r2": null,
      "diam": 0.51,
      "e_diam": 0.05,
      "mass": 212.36,
      "e_mass": 43.38,
      "blum": 283.93,
      "e_blum": 57.95,
      "lmrat": 1.34,
      "e_lmrat": 0.39,
      "temp": 12.4,
      "e_temp": 0.6,
      "lrat": 29.9,
      "e_lrat": 5.98,
      "tbol": 58.35,
      "e_tbol": 11.67,
      "sigma": 0.22,
      "e_sigma": 0.04,
      "glon": 80.36234,
      "glat": 0.76616,
      "mwpr": 0.00477,
      "e_glon": 0.00061,
      "e_glat": 0.00038,
      "e_mwpr": 0.00195,
      "hrate": 0.4,
      "f8": 0.2297,
      "e_f8": 0.7111,
      "f12": 0.1479,
      "e_f12": 0.6316,
      "f24": 0.7449,
      "e_f24": 0.5521,
      "f70": 4.6608,
      "e_f70": 0.8522,
      "n8": 6,
      "n12": 6,
      "n24": 6,
      "n70": 6,
      "f_sat": "0000",
      "f_multi": 1,
      "f_nosrc": "0000",
      "f_pconf": "1000",
      "f_cext": 0,
      "vlsr": -24.34,
      "e_vlsr": 0.18,
      "stype": "OUT",
      "vlsr_g": null,
      "vlsr_s": null,
      "vlsr_f": null,
      "vlsr_t": null,
      "vlsr_dht": null,
      "vlsr_dgt": null,
      "dgt": null,
      "vlsr_c": -24.3,
      "vlsr_m": -24.34,
      "e_vlsr_m": 0.18,
      "higal": "HIGALBM80.3634+0.7682",
      "agal": null,
      "corn": null,
      "corn_t": null,
      "rms": null,
      "rms_t": null,
      "wise": null,
      "wise_t": null
    }
  ]
}
