{
  "Sources": [
    {
      "source": "YB2950",
      "yb_number": 2950,
      "reference": "WolfChase25",
      "dist": 4.3,
      "e_dist": 0.82,
      "dist_c": -1.0,
      "dist_m": 0.0,
      "e_dist_m": 0.0,
      "stat_m": "KDA_NO",
      "pfar": 0.5,
      "dist_r1": 4.3,
      "e_dist_r1": 0.82,
      "pint_r1": 0.36,
      "arm_r1": null,
      "dist_r2": 1.58,
      "e_dist_r2": 0.1,
      "pint_r2": 0.28,
      "arm_r2": null,
      "diam": 0.26,
      "e_diam": 0.05,
      "mass": 22.19,
      "e_mass": 8.46,
      "blum": 109.09,
      "e_blum": 41.61,
      "lmrat": 4.92,
      "e_lmrat": 2.65,
      "temp": 15.9,
      "e_temp": 0.2,
      "lrat": 56.5,
      "e_lrat": 11.3,
      "tbol": 46.69,
      "e_tbol": 9.34,
      "sigma": 0.09,
      "e_sigma": 0.03,
      "glon": 80.74536,
      "glat": 2.03644,
      "mwpr": 0.00389,
      "e_glon": 0.00054,
      "e_glat": 0.00051,
      "e_mwpr": 0.00124,
      "hrate": 0.76,
      "f8": 0.1002,
      "e_f8": 0.1695,
      "f12": 0.0395,
      "e_f12": 0.5773,
      "f24": 0.0963,
      "e_f24": 0.2907,
      "f70": 1.0969,
      "e_f70": 0.2595,
      "n8": 6,
      "n12": 6,
      "n24": 6,
      "n70": 6,
      "f_sat": "0000",
      "f_multi": 0,
      "f_nosrc": "0000",
      "f_pconf": "0000",
      "f_cext": 0,
      "vlsr": -7.8,
      "e_vlsr": 0.65,
      "stype": "SP",
      "vlsr_g": null,
      "vlsr_s": null,
      "vlsr_f": null,
      "vlsr_t": null,
      "vlsr_dht": -7.8,
      "vlsr_dgt": null,
      "dgt": null,
      "vlsr_c": null,
      "vlsr_m": null,
      "e_vlsr_m": null,
      "higal": "HIGALBM80.7464+2.0374",
      "agal": null,
      "corn": null,
      "corn_t": null,
      "rms": null,
      "rms_t": null,
      "wise": null,
      "wise_t": null
    }
  ]
}
