{
  "Sources": [
    {
      "source": "YB3002",
      "yb_number": 3002,
      "reference": "WolfChase25",
      "dist": 1.56,
      "e_dist": 0.11,
      "dist_c": 2.98,
      "dist_m": 2.98,
      "e_dist_m": 0.95,
      "stat_m": "NO_AMB",
      "pfar": 1.0,
      "dist_r1": 1.56,
      "e_dist_r1": 0.11,
      "pint_r1": 0.55,
      "arm_r1": "Loc",
      "dist_r2": 2.19,
      "e_dist_r2": 0.41,
      "pint_r2": 0.45,
      "arm_r2": "Loc",
      "diam": 0.31,
      "e_diam": 0.02,
      "mass": 94.6,
      "e_mass": 14.17,
      "blum": 106.9,
      "e_blum": 15.08,
      "lmrat": 1.13,
      "e_lmrat": 0.23,
      "temp": 11.7,
      "e_temp": 0.7,
      "lrat": 29.3,
      "e_lrat": 5.86,
      "tbol": 53.95,
      "e_tbol": 10.79,
      "sigma": 0.27,
      "e_sigma": 0.04,
      "glon": 81.84877,
      "glat": 0.75545,
      "mwpr": 0.00668,
      "e_glon": 0.00066,
      "e_glat": 0.00084,
      "e_mwpr": 0.00214,
      "hrate": 0.75,
      "f8": 1.5304,
      "e_f8": 0.913,
      "f12": 0.5261,
      "e_f12": 1.1949,
      "f24": 1.5191,
      "e_f24": 0.6633,
      "f70": 22.3238,
      "e_f70": 0.8629,
      "n8": 6,
      "n12": 6,
      "n24": 6,
      "n70": 6,
      "f_sat": "0000",
      "f_multi": 0,
      "f_nosrc": "0000",
      "f_pconf": "0011",
      "f_cext": 0,
      "vlsr": -3.13,
      "e_vlsr": 0.02,
      "stype": "OUT",
      "vlsr_g": null,
      "vlsr_s": null,
      "vlsr_f": null,
      "vlsr_t": null,
      "vlsr_dht": null,
      "vlsr_dgt": null,
      "dgt": null,
      "vlsr_c": -3.1,
      "vlsr_m": -3.13,
      "e_vlsr_m": 0.02,
      "higal": "HIGALBM81.8506+0.7552",
      "agal": null,
      "corn": null,
      "corn_t": null,
      "rms": null,
      "rms_t": null,
      "wise": "G081.845+00.750",
      "wise_t": "Q"
    }
  ]
}
