{
  "Sources": [
    {
      "source": "YB3387",
      "yb_number": 3387,
      "reference": "WolfChase25",
      "dist": 7.14,
      "e_dist": 0.73,
      "dist_c": 6.95,
      "dist_m": 6.98,
      "e_dist_m": 0.7,
      "stat_m": "NO_KDA",
      "pfar": 0.5,
      "dist_r1": 7.14,
      "e_dist_r1": 0.73,
      "pint_r1": 0.44,
      "arm_r1": null,
      "dist_r2": 2.0,
      "e_dist_r2": 0.29,
      "pint_r2": 0.34,
      "arm_r2": "CrN",
      "diam": 0.95,
      "e_diam": 0.1,
      "mass": 362.33,
      "e_mass": 388.04,
      "blum": 6150.69,
      "e_blum": 1759.28,
      "lmrat": 16.98,
      "e_lmrat": 18.82,
      "temp": 18.7,
      "e_temp": 0.8,
      "lrat": 137.1,
      "e_lrat": 27.42,
      "tbol": 48.02,
      "e_tbol": 9.6,
      "sigma": 0.11,
      "e_sigma": 0.12,
      "glon": 298.40977,
      "glat": -0.73569,
      "mwpr": 0.00503,
      "e_glon": 0.00048,
      "e_glat": 0.0004,
      "e_mwpr": 0.00143,
      "hrate": 0.82,
      "f8": 0.9585,
      "e_f8": 0.121,
      "f12": 0.3614,
      "e_f12": 0.2891,
      "f24": 0.9785,
      "e_f24": 0.1793,
      "f70": 19.6054,
      "e_f70": 0.5415,
      "n8": 5,
      "n12": 5,
      "n24": 5,
      "n70": 5,
      "f_sat": "0000",
      "f_multi": 1,
      "f_nosrc": "0000",
      "f_pconf": "0000",
      "f_cext": 0,
      "vlsr": -11.15,
      "e_vlsr": 0.11,
      "stype": "OUT",
      "vlsr_g": null,
      "vlsr_s": null,
      "vlsr_f": null,
      "vlsr_t": null,
      "vlsr_dht": null,
      "vlsr_dgt": null,
      "dgt": null,
      "vlsr_c": -11.4,
      "vlsr_m": -11.15,
      "e_vlsr_m": 0.11,
      "higal": "HIGALBM298.4094-0.7349",
      "agal": null,
      "corn": null,
      "corn_t": null,
      "rms": null,
      "rms_t": null,
      "wise": "G298.410-00.737",
      "wise_t": "Q"
    }
  ]
}
