{
  "Sources": [
    {
      "source": "YB3957",
      "yb_number": 3957,
      "reference": "WolfChase25",
      "dist": 7.51,
      "e_dist": 0.85,
      "dist_c": 7.54,
      "dist_m": 7.55,
      "e_dist_m": 0.6,
      "stat_m": "SDIST_EXT",
      "pfar": 1.0,
      "dist_r1": 7.51,
      "e_dist_r1": 0.85,
      "pint_r1": 0.97,
      "arm_r1": null,
      "dist_r2": 5.48,
      "e_dist_r2": 0.07,
      "pint_r2": 0.03,
      "arm_r2": "CtN",
      "diam": 0.53,
      "e_diam": 0.06,
      "mass": 498.31,
      "e_mass": 123.79,
      "blum": 32986.33,
      "e_blum": 7466.95,
      "lmrat": 66.2,
      "e_lmrat": 22.25,
      "temp": 26.4,
      "e_temp": 0.9,
      "lrat": 278.1,
      "e_lrat": 55.62,
      "tbol": 58.39,
      "e_tbol": 11.68,
      "sigma": 0.48,
      "e_sigma": 0.12,
      "glon": 311.42428,
      "glat": 0.59685,
      "mwpr": 0.00542,
      "e_glon": 0.00191,
      "e_glat": 0.00135,
      "e_mwpr": 0.00137,
      "hrate": 0.48,
      "f8": 7.6441,
      "e_f8": 0.1049,
      "f12": 2.0566,
      "e_f12": 0.211,
      "f24": null,
      "e_f24": null,
      "f70": 248.6074,
      "e_f70": 0.1204,
      "n8": 5,
      "n12": 5,
      "n24": 0,
      "n70": 5,
      "f_sat": "0010",
      "f_multi": 0,
      "f_nosrc": "0000",
      "f_pconf": "0000",
      "f_cext": 0,
      "vlsr": -48.63,
      "e_vlsr": 0.15,
      "stype": "LSNR",
      "vlsr_g": null,
      "vlsr_s": null,
      "vlsr_f": null,
      "vlsr_t": -48.63,
      "vlsr_dht": null,
      "vlsr_dgt": null,
      "dgt": null,
      "vlsr_c": -48.6,
      "vlsr_m": -48.38,
      "e_vlsr_m": 0.22,
      "higal": "HIGALBM311.4268+0.5962",
      "agal": "G311.4243+0.5963",
      "corn": "G311.4260+0.5967",
      "corn_t": "HII Region",
      "rms": "G311.4255+00.5964",
      "rms_t": "HII region",
      "wise": "G311.425+00.598",
      "wise_t": "C"
    }
  ]
}
