{
  "Sources": [
    {
      "source": "YB4100",
      "yb_number": 4100,
      "reference": "WolfChase25",
      "dist": 11.41,
      "e_dist": 0.53,
      "dist_c": 4.13,
      "dist_m": 4.13,
      "e_dist_m": 0.64,
      "stat_m": "CLOUD_EXT",
      "pfar": 0.0,
      "dist_r1": 11.41,
      "e_dist_r1": 0.53,
      "pint_r1": 1.0,
      "arm_r1": "?",
      "dist_r2": 0.0,
      "e_dist_r2": 0.0,
      "pint_r2": 0.0,
      "arm_r2": null,
      "diam": 1.33,
      "e_diam": 0.06,
      "mass": 2094.38,
      "e_mass": 1688.13,
      "blum": 36777.57,
      "e_blum": 8110.32,
      "lmrat": 17.56,
      "e_lmrat": 14.67,
      "temp": 16.6,
      "e_temp": 1.1,
      "lrat": 187.6,
      "e_lrat": 37.52,
      "tbol": 54.88,
      "e_tbol": 10.98,
      "sigma": 0.32,
      "e_sigma": 0.26,
      "glon": 313.78286,
      "glat": 0.70789,
      "mwpr": 0.00555,
      "e_glon": 0.00092,
      "e_glat": 0.00068,
      "e_mwpr": 0.00076,
      "hrate": 0.42,
      "f8": 1.604,
      "e_f8": 0.3802,
      "f12": 0.8929,
      "e_f12": 0.5973,
      "f24": 3.852,
      "e_f24": 1.327,
      "f70": 59.4907,
      "e_f70": 0.38,
      "n8": 5,
      "n12": 5,
      "n24": 5,
      "n70": 5,
      "f_sat": "0000",
      "f_multi": 0,
      "f_nosrc": "0000",
      "f_pconf": "1101",
      "f_cext": 0,
      "vlsr": -58.44,
      "e_vlsr": 0.15,
      "stype": "LSNR",
      "vlsr_g": null,
      "vlsr_s": null,
      "vlsr_f": null,
      "vlsr_t": -58.44,
      "vlsr_dht": null,
      "vlsr_dgt": null,
      "dgt": null,
      "vlsr_c": -58.2,
      "vlsr_m": -58.2,
      "e_vlsr_m": 0.18,
      "higal": "HIGALBM313.7794+0.7087",
      "agal": "CSC313.779+00.709",
      "corn": "G313.7830+0.7101",
      "corn_t": "HII Region",
      "rms": null,
      "rms_t": null,
      "wise": null,
      "wise_t": null
    }
  ]
}
