{
  "Sources": [
    {
      "source": "YB4607",
      "yb_number": 4607,
      "reference": "WolfChase25",
      "dist": 3.24,
      "e_dist": 0.28,
      "dist_c": 3.75,
      "dist_m": 3.72,
      "e_dist_m": 0.36,
      "stat_m": "KDIST_IRDC",
      "pfar": 0.0,
      "dist_r1": 3.24,
      "e_dist_r1": 0.28,
      "pint_r1": 0.98,
      "arm_r1": "CtN",
      "dist_r2": 6.76,
      "e_dist_r2": 0.06,
      "pint_r2": 0.02,
      "arm_r2": "N4F",
      "diam": 0.43,
      "e_diam": 0.04,
      "mass": 134.0,
      "e_mass": 141.43,
      "blum": 379.0,
      "e_blum": 100.18,
      "lmrat": 2.83,
      "e_lmrat": 3.08,
      "temp": 13.9,
      "e_temp": 0.4,
      "lrat": 46.1,
      "e_lrat": 9.22,
      "tbol": 49.62,
      "e_tbol": 9.92,
      "sigma": 0.19,
      "e_sigma": 0.2,
      "glon": 327.20989,
      "glat": -0.20012,
      "mwpr": 0.00357,
      "e_glon": 0.00027,
      "e_glat": 0.00057,
      "e_mwpr": 0.00183,
      "hrate": 0.16,
      "f8": 0.7298,
      "e_f8": 0.1249,
      "f12": 0.2542,
      "e_f12": 0.0925,
      "f24": 0.7083,
      "e_f24": 0.0647,
      "f70": 9.6304,
      "e_f70": 0.0457,
      "n8": 5,
      "n12": 5,
      "n24": 5,
      "n70": 5,
      "f_sat": "0000",
      "f_multi": 0,
      "f_nosrc": "0000",
      "f_pconf": "0000",
      "f_cext": 0,
      "vlsr": -63.0,
      "e_vlsr": 0.13,
      "stype": "SP",
      "vlsr_g": null,
      "vlsr_s": -63.0,
      "vlsr_f": null,
      "vlsr_t": null,
      "vlsr_dht": null,
      "vlsr_dgt": null,
      "dgt": null,
      "vlsr_c": -63.9,
      "vlsr_m": -63.44,
      "e_vlsr_m": 0.09,
      "higal": "HIGALBM327.2108-0.2003",
      "agal": null,
      "corn": null,
      "corn_t": null,
      "rms": null,
      "rms_t": null,
      "wise": null,
      "wise_t": null
    }
  ]
}
