{
  "Sources": [
    {
      "source": "YB508",
      "yb_number": 508,
      "reference": "WolfChase25",
      "dist": 1.42,
      "e_dist": 0.25,
      "dist_c": 11.81,
      "dist_m": 11.81,
      "e_dist_m": 0.33,
      "stat_m": "NO_KDA",
      "pfar": 0.5,
      "dist_r1": 1.42,
      "e_dist_r1": 0.25,
      "pint_r1": 0.36,
      "arm_r1": "SgN",
      "dist_r2": 1.84,
      "e_dist_r2": 0.08,
      "pint_r2": 0.27,
      "arm_r2": "SgN",
      "diam": 0.08,
      "e_diam": 0.01,
      "mass": 15.01,
      "e_mass": 5.71,
      "blum": 109.48,
      "e_blum": 38.55,
      "lmrat": 7.29,
      "e_lmrat": 3.78,
      "temp": 16.3,
      "e_temp": 0.3,
      "lrat": 81.7,
      "e_lrat": 16.34,
      "tbol": 60.65,
      "e_tbol": 12.13,
      "sigma": 0.62,
      "e_sigma": 0.24,
      "glon": 15.65404,
      "glat": -0.22454,
      "mwpr": 0.00272,
      "e_glon": 0.0003,
      "e_glat": 0.00045,
      "e_mwpr": 0.00102,
      "hrate": 0.11,
      "f8": 0.2186,
      "e_f8": 0.5232,
      "f12": 0.0654,
      "e_f12": 0.4647,
      "f24": 1.4451,
      "e_f24": 0.1875,
      "f70": 15.3828,
      "e_f70": 0.1124,
      "n8": 5,
      "n12": 5,
      "n24": 5,
      "n70": 5,
      "f_sat": "0000",
      "f_multi": 0,
      "f_nosrc": "0000",
      "f_pconf": "0000",
      "f_cext": 0,
      "vlsr": 17.79,
      "e_vlsr": 0.1,
      "stype": "MP:3",
      "vlsr_g": 17.79,
      "vlsr_s": 57.0,
      "vlsr_f": null,
      "vlsr_t": null,
      "vlsr_dht": null,
      "vlsr_dgt": null,
      "dgt": null,
      "vlsr_c": 56.4,
      "vlsr_m": 56.44,
      "e_vlsr_m": 0.12,
      "higal": "HIGALBM15.6538-0.2243",
      "agal": "CSC015.653-00.219",
      "corn": null,
      "corn_t": null,
      "rms": null,
      "rms_t": null,
      "wise": null,
      "wise_t": null
    }
  ]
}
