{
  "Sources": [
    {
      "source": "YB5110",
      "yb_number": 5110,
      "reference": "WolfChase25",
      "dist": 10.99,
      "e_dist": 0.62,
      "dist_c": 11.13,
      "dist_m": 11.24,
      "e_dist_m": 0.32,
      "stat_m": "SDIST_EXT",
      "pfar": 1.0,
      "dist_r1": 10.99,
      "e_dist_r1": 0.62,
      "pint_r1": 0.97,
      "arm_r1": "N4F",
      "dist_r2": 4.52,
      "e_dist_r2": 0.23,
      "pint_r2": 0.03,
      "arm_r2": "N4N",
      "diam": 0.68,
      "e_diam": 0.04,
      "mass": 1411.12,
      "e_mass": 232.66,
      "blum": 16528.22,
      "e_blum": 1864.88,
      "lmrat": 11.71,
      "e_lmrat": 2.34,
      "temp": 18.1,
      "e_temp": 0.4,
      "lrat": 104.4,
      "e_lrat": 20.88,
      "tbol": 55.2,
      "e_tbol": 11.04,
      "sigma": 0.81,
      "e_sigma": 0.13,
      "glon": 335.7321,
      "glat": -0.09343,
      "mwpr": 0.00361,
      "e_glon": 0.00032,
      "e_glat": 0.00038,
      "e_mwpr": 0.0016,
      "hrate": 0.22,
      "f8": 0.532,
      "e_f8": 0.4719,
      "f12": 0.0481,
      "e_f12": 0.4998,
      "f24": 0.8521,
      "e_f24": 0.3785,
      "f70": 20.9599,
      "e_f70": 0.4152,
      "n8": 5,
      "n12": 5,
      "n24": 5,
      "n70": 5,
      "f_sat": "0000",
      "f_multi": 1,
      "f_nosrc": "0000",
      "f_pconf": "0000",
      "f_cext": 0,
      "vlsr": -67.0,
      "e_vlsr": 0.13,
      "stype": "SP",
      "vlsr_g": null,
      "vlsr_s": -67.0,
      "vlsr_f": null,
      "vlsr_t": null,
      "vlsr_dht": null,
      "vlsr_dgt": null,
      "dgt": null,
      "vlsr_c": -67.1,
      "vlsr_m": -64.7,
      "e_vlsr_m": 1.18,
      "higal": "HIGALBM335.7276-0.0965",
      "agal": "G335.7293-0.0977",
      "corn": null,
      "corn_t": null,
      "rms": "G335.7288-00.0966",
      "rms_t": "YSO",
      "wise": null,
      "wise_t": null
    }
  ]
}
