{
  "Sources": [
    {
      "source": "YB5127",
      "yb_number": 5127,
      "reference": "WolfChase25",
      "dist": 1.4,
      "e_dist": 0.28,
      "dist_c": 1.4,
      "dist_m": 1.4,
      "e_dist_m": 0.28,
      "stat_m": "SDIST_GROUP",
      "pfar": 0.5,
      "dist_r1": 2.56,
      "e_dist_r1": 0.36,
      "pint_r1": 0.9,
      "arm_r1": "CtN",
      "dist_r2": 1.48,
      "e_dist_r2": 0.21,
      "pint_r2": 0.09,
      "arm_r2": null,
      "diam": 0.13,
      "e_diam": 0.03,
      "mass": 15.5,
      "e_mass": 228.38,
      "blum": 54.4,
      "e_blum": 24.33,
      "lmrat": 3.51,
      "e_lmrat": 51.74,
      "temp": 14.0,
      "e_temp": 0.2,
      "lrat": 55.9,
      "e_lrat": 11.18,
      "tbol": 48.23,
      "e_tbol": 9.65,
      "sigma": 0.25,
      "e_sigma": 3.68,
      "glon": 336.05797,
      "glat": -0.1617,
      "mwpr": 0.00222,
      "e_glon": 0.00019,
      "e_glat": 0.00025,
      "e_mwpr": 0.00039,
      "hrate": 0.27,
      "f8": 0.2181,
      "e_f8": 0.1124,
      "f12": 0.0548,
      "e_f12": 0.3634,
      "f24": 0.176,
      "e_f24": 0.2349,
      "f70": 6.4803,
      "e_f70": 0.1877,
      "n8": 5,
      "n12": 5,
      "n24": 5,
      "n70": 5,
      "f_sat": "0000",
      "f_multi": 0,
      "f_nosrc": "0000",
      "f_pconf": "0000",
      "f_cext": 0,
      "vlsr": -26.75,
      "e_vlsr": 0.13,
      "stype": "SP",
      "vlsr_g": null,
      "vlsr_s": -26.75,
      "vlsr_f": null,
      "vlsr_t": null,
      "vlsr_dht": null,
      "vlsr_dgt": null,
      "dgt": null,
      "vlsr_c": -26.4,
      "vlsr_m": -26.44,
      "e_vlsr_m": 0.06,
      "higal": "HIGALBM336.0581-0.1612",
      "agal": null,
      "corn": null,
      "corn_t": null,
      "rms": null,
      "rms_t": null,
      "wise": null,
      "wise_t": null
    }
  ]
}
