{
  "Sources": [
    {
      "source": "YB5800",
      "yb_number": 5800,
      "reference": "WolfChase25",
      "dist": 2.2,
      "e_dist": 0.44,
      "dist_c": 2.2,
      "dist_m": 2.2,
      "e_dist_m": 0.44,
      "stat_m": "SDIST_GROUP",
      "pfar": 0.5,
      "dist_r1": 12.05,
      "e_dist_r1": 0.43,
      "pint_r1": 0.46,
      "arm_r1": "Per",
      "dist_r2": 2.86,
      "e_dist_r2": 0.34,
      "pint_r2": 0.31,
      "arm_r2": "CtN",
      "diam": 0.06,
      "e_diam": 0.01,
      "mass": 1.9,
      "e_mass": 28.71,
      "blum": 181.5,
      "e_blum": 81.17,
      "lmrat": 95.53,
      "e_lmrat": 1444.09,
      "temp": 32.8,
      "e_temp": 1.9,
      "lrat": 170.5,
      "e_lrat": 34.1,
      "tbol": 46.71,
      "e_tbol": 9.34,
      "sigma": 0.13,
      "e_sigma": 1.96,
      "glon": 349.35764,
      "glat": 0.11964,
      "mwpr": 0.00224,
      "e_glon": 0.00036,
      "e_glat": 0.00013,
      "e_mwpr": 0.00122,
      "hrate": 0.35,
      "f8": 0.1578,
      "e_f8": 0.3455,
      "f12": 0.0508,
      "e_f12": 0.3082,
      "f24": 0.3344,
      "e_f24": 0.1703,
      "f70": 15.0139,
      "e_f70": 0.1142,
      "n8": 5,
      "n12": 5,
      "n24": 5,
      "n70": 5,
      "f_sat": "0000",
      "f_multi": 0,
      "f_nosrc": "0000",
      "f_pconf": "0000",
      "f_cext": 0,
      "vlsr": -21.75,
      "e_vlsr": 0.13,
      "stype": "SP",
      "vlsr_g": null,
      "vlsr_s": -21.75,
      "vlsr_f": null,
      "vlsr_t": null,
      "vlsr_dht": null,
      "vlsr_dgt": null,
      "dgt": null,
      "vlsr_c": -21.7,
      "vlsr_m": -21.69,
      "e_vlsr_m": 0.11,
      "higal": "HIGALBM349.3577+0.1201",
      "agal": null,
      "corn": null,
      "corn_t": null,
      "rms": null,
      "rms_t": null,
      "wise": "G349.357+00.120",
      "wise_t": "Q"
    }
  ]
}
