{
  "Sources": [
    {
      "source": "YB637",
      "yb_number": 637,
      "reference": "WolfChase25",
      "dist": 1.5,
      "e_dist": 0.04,
      "dist_c": 14.09,
      "dist_m": 14.11,
      "e_dist_m": 0.59,
      "stat_m": "SDIST_EXT",
      "pfar": 1.0,
      "dist_r1": 1.5,
      "e_dist_r1": 0.04,
      "pint_r1": 0.49,
      "arm_r1": "SgN",
      "dist_r2": 13.35,
      "e_dist_r2": 0.38,
      "pint_r2": 0.23,
      "arm_r2": "Per",
      "diam": 0.2,
      "e_diam": 0.01,
      "mass": 24.06,
      "e_mass": 24.24,
      "blum": 206.71,
      "e_blum": 42.79,
      "lmrat": 8.59,
      "e_lmrat": 8.84,
      "temp": 15.5,
      "e_temp": 1.0,
      "lrat": 107.5,
      "e_lrat": 21.5,
      "tbol": 69.68,
      "e_tbol": 13.94,
      "sigma": 0.15,
      "e_sigma": 0.15,
      "glon": 18.58708,
      "glat": 0.34485,
      "mwpr": 0.00174,
      "e_glon": 0.00049,
      "e_glat": 0.00043,
      "e_mwpr": 0.00032,
      "hrate": 0.23,
      "f8": 0.1854,
      "e_f8": 0.6012,
      "f12": 0.1098,
      "e_f12": 0.5517,
      "f24": 1.211,
      "e_f24": 0.8414,
      "f70": 8.2788,
      "e_f70": 0.7033,
      "n8": 5,
      "n12": 5,
      "n24": 5,
      "n70": 5,
      "f_sat": "0000",
      "f_multi": 0,
      "f_nosrc": "0000",
      "f_pconf": "0001",
      "f_cext": 0,
      "vlsr": 18.85,
      "e_vlsr": 0.1,
      "stype": "SP",
      "vlsr_g": 18.85,
      "vlsr_s": null,
      "vlsr_f": null,
      "vlsr_t": null,
      "vlsr_dht": null,
      "vlsr_dgt": null,
      "dgt": null,
      "vlsr_c": 18.4,
      "vlsr_m": 18.16,
      "e_vlsr_m": 0.97,
      "higal": "HIGALBM18.5872+0.3450",
      "agal": null,
      "corn": null,
      "corn_t": null,
      "rms": null,
      "rms_t": null,
      "wise": "G018.584+00.344",
      "wise_t": "K"
    }
  ]
}
