{
  "Sources": [
    {
      "source": "YB754",
      "yb_number": 754,
      "reference": "WolfChase25",
      "dist": 8.64,
      "e_dist": 2.17,
      "dist_c": 10.4,
      "dist_m": 12.14,
      "e_dist_m": 0.36,
      "stat_m": "NO_KDA",
      "pfar": 0.5,
      "dist_r1": 8.64,
      "e_dist_r1": 2.17,
      "pint_r1": 0.55,
      "arm_r1": null,
      "dist_r2": 4.53,
      "e_dist_r2": 0.74,
      "pint_r2": 0.45,
      "arm_r2": "N1N",
      "diam": 0.34,
      "e_diam": 0.09,
      "mass": 474.57,
      "e_mass": 242.66,
      "blum": 6410.58,
      "e_blum": 3220.13,
      "lmrat": 13.51,
      "e_lmrat": 9.68,
      "temp": 20.9,
      "e_temp": 0.4,
      "lrat": 89.4,
      "e_lrat": 17.88,
      "tbol": 42.08,
      "e_tbol": 8.42,
      "sigma": 1.07,
      "e_sigma": 0.55,
      "glon": 21.4066,
      "glat": -0.25449,
      "mwpr": 0.00167,
      "e_glon": 0.00025,
      "e_glat": 0.00043,
      "e_mwpr": 0.00024,
      "hrate": 0.35,
      "f8": 0.1126,
      "e_f8": 0.0991,
      "f12": 0.0244,
      "e_f12": 0.4389,
      "f24": 0.1058,
      "e_f24": 0.2811,
      "f70": 22.2071,
      "e_f70": 0.1293,
      "n8": 6,
      "n12": 6,
      "n24": 6,
      "n70": 6,
      "f_sat": "0000",
      "f_multi": 1,
      "f_nosrc": "0000",
      "f_pconf": "0000",
      "f_cext": 0,
      "vlsr": 91.54,
      "e_vlsr": 0.1,
      "stype": "SP",
      "vlsr_g": 91.54,
      "vlsr_s": null,
      "vlsr_f": null,
      "vlsr_t": null,
      "vlsr_dht": null,
      "vlsr_dgt": null,
      "dgt": null,
      "vlsr_c": 90.6,
      "vlsr_m": 48.7,
      "e_vlsr_m": 0.31,
      "higal": "HIGALBM21.4068-0.2538",
      "agal": "G021.4062-0.2530",
      "corn": null,
      "corn_t": null,
      "rms": null,
      "rms_t": null,
      "wise": null,
      "wise_t": null
    }
  ]
}
